pudzu/charts/__init__.py
pudzu/charts/charts.py
pudzu_charts-0.9.3.dist-info/METADATA
pudzu_charts-0.9.3.dist-info/WHEEL
pudzu_charts-0.9.3.dist-info/RECORD
