Metadata-Version: 2.1
Name: pudzu-charts
Version: 0.9.3
Summary: Pillow-based charting tools
Home-page: https://github.com/Udzu/pudzu-packages/pudzu-charts/
License: MIT
Keywords: pudzu,charts,pillow
Author: Uri Granta
Author-email: uri.granta+python@gmail.com
Requires-Python: >=3.8,<4.0
Classifier: License :: OSI Approved :: MIT License
Classifier: Operating System :: OS Independent
Classifier: Programming Language :: Python :: 3
Classifier: Programming Language :: Python :: 3.8
Classifier: Programming Language :: Python :: 3.9
Classifier: Programming Language :: Python :: 3.10
Classifier: Programming Language :: Python :: 3.11
Classifier: Programming Language :: Python :: 3.12
Requires-Dist: pandas (>=1.4,<2.0)
Requires-Dist: pudzu-dates (>=0.9.3,<0.10.0)
Requires-Dist: pudzu-pillar (>=0.9.3,<0.10.0)
Requires-Dist: pudzu-utils (>=0.9.3,<0.10.0)
